beers/__init__.py
beers/_version.py
beers/models.py
beers/nvidia.py
beers/utils.py
beers/worker_utils.py
beers/bot/__init__.py
beers/bot/job.py
beers/bot/telegram_bot.py
beers/manager/__init__.py
beers/manager/api.py
beers/manager/beer_db.py
beers/manager/service.py
beers/scripts/__init__.py
beers/scripts/beers
beers/scripts/worker_setup.sh
beers-0.1.2.data/data/setup.cfg
beers-0.1.2.data/scripts/beers
beers-0.1.2.dist-info/LICENSE
beers-0.1.2.dist-info/METADATA
beers-0.1.2.dist-info/WHEEL
beers-0.1.2.dist-info/top_level.txt
beers-0.1.2.dist-info/RECORD
