Metadata-Version: 2.1
Name: beers
Version: 0.1.2
Summary: Better Enabled Resource Sharing
Home-page: https://github.com/grok-ai/BeERS
Author: Valentino Maiorca
Author-email: valentino@maiorca.xyz
License: MIT Licence
Keywords: python
Platform: UNKNOWN
License-File: LICENSE
Requires-Dist: orjson
Requires-Dist: requests
Requires-Dist: typer
Requires-Dist: schedule
Requires-Dist: rich
Requires-Dist: python-dotenv
Requires-Dist: pydantic
Provides-Extra: bot
Requires-Dist: python-telegram-bot ; extra == 'bot'
Provides-Extra: dev
Requires-Dist: black ; extra == 'dev'
Requires-Dist: flake8 ; extra == 'dev'
Requires-Dist: isort ; extra == 'dev'
Requires-Dist: pre-commit ; extra == 'dev'
Requires-Dist: bandit ; extra == 'dev'
Requires-Dist: pytest ; extra == 'dev'
Requires-Dist: pytest-cov ; extra == 'dev'
Requires-Dist: mkdocs ; extra == 'dev'
Requires-Dist: mkdocs-material ; extra == 'dev'
Requires-Dist: mike ; extra == 'dev'
Requires-Dist: peewee ; extra == 'dev'
Requires-Dist: docker ; extra == 'dev'
Requires-Dist: fastapi ; extra == 'dev'
Requires-Dist: uvicorn[standard] ; extra == 'dev'
Requires-Dist: python-telegram-bot ; extra == 'dev'
Requires-Dist: psutil ; extra == 'dev'
Provides-Extra: docs
Requires-Dist: mkdocs ; extra == 'docs'
Requires-Dist: mkdocs-material ; extra == 'docs'
Requires-Dist: mike ; extra == 'docs'
Provides-Extra: manager
Requires-Dist: peewee ; extra == 'manager'
Requires-Dist: docker ; extra == 'manager'
Requires-Dist: fastapi ; extra == 'manager'
Requires-Dist: uvicorn[standard] ; extra == 'manager'
Provides-Extra: test
Requires-Dist: pytest ; extra == 'test'
Requires-Dist: pytest-cov ; extra == 'test'
Provides-Extra: worker
Requires-Dist: docker ; extra == 'worker'
Requires-Dist: psutil ; extra == 'worker'
